obshell_mcp/__init__.py
obshell_mcp/__main__.py
obshell_mcp/server.py
obshell_mcp-0.0.1.dist-info/licenses/LICENSE
obshell_mcp-0.0.1.dist-info/METADATA
obshell_mcp-0.0.1.dist-info/WHEEL
obshell_mcp-0.0.1.dist-info/entry_points.txt
obshell_mcp-0.0.1.dist-info/top_level.txt
obshell_mcp-0.0.1.dist-info/RECORD
