Metadata-Version: 2.4
Name: obshell-mcp
Version: 0.0.1
Summary: obshell MCP Server
License:                                  Apache License
Keywords: oceanbase,obshell,mcp
Classifier: Development Status :: 3 - Alpha
Classifier: Programming Language :: Python :: 3
Classifier: Programming Language :: Python :: 3.10
Requires-Python: >=3.10
License-File: LICENSE
Requires-Dist: fastmcp>=1.0
Requires-Dist: uvicorn>=0.27.1
Requires-Dist: obshell>=0.0.6
Dynamic: license-file
